cloudwright_aws_boto3/__init__.py
cloudwright_aws_boto3-0.0.0.dist-info/METADATA
cloudwright_aws_boto3-0.0.0.dist-info/WHEEL
cloudwright_aws_boto3-0.0.0.dist-info/top_level.txt
cloudwright_aws_boto3-0.0.0.dist-info/RECORD
